JpegIPTC.py
JpegIPTC-1.5.dist-info/LICENSE
JpegIPTC-1.5.dist-info/METADATA
JpegIPTC-1.5.dist-info/WHEEL
JpegIPTC-1.5.dist-info/top_level.txt
JpegIPTC-1.5.dist-info/RECORD
