Metadata-Version: 2.1
Name: JpegIPTC
Version: 1.5
Summary: Jpeg Iptc data raw extract/copy
Home-page: https://github.com/gdegoulet/JpegIPTC
Download-URL: https://github.com/gdegoulet/JpegIPTC
Author: Guillaume Degoulet
Author-email: jpegiptc@degoulet.net
Maintainer: Guillaume Degoulet
Maintainer-email: jpegiptc@degoulet.net
License: http://www.opensource.org/licenses/gpl-license.php
Platform: any
Classifier: Development Status :: 3 - Alpha
Classifier: License :: OSI Approved :: Artistic License
Classifier: License :: OSI Approved :: GNU General Public License (GPL)
Classifier: Intended Audience :: Developers
Classifier: Programming Language :: Python
Classifier: Topic :: Multimedia :: Graphics
Classifier: Topic :: Utilities
License-File: LICENSE
